{"input_sentence": "Marco Rubio voted against authorizing President Obama to strike Syria after Assad used chemical weapons on his own people", "frame_elements": {"Agent": {"start": 0, "end": 11}, "Issue": {"start": 26, "end": 121}, "Side": {"start": -1, "end": -1}, "Position": {"start": 18, "end": 25}, "Frequency": {"start": -1, "end": -1}, "Time": {"start": -1, "end": -1}, "Place": {"start": -1, "end": -1}, "Support_rate": {"start": -1, "end": -1}}, "bills": [], "member_id": "R000595", "congress_member": "Marco Rubio"}